alda_pipeline/Project.py
alda_pipeline/__init__.py
alda_pipeline/test_int_main.py
alda_pipeline/test_main.py
example_pkg_alda_pipeline-0.0.1.dist-info/METADATA
example_pkg_alda_pipeline-0.0.1.dist-info/WHEEL
example_pkg_alda_pipeline-0.0.1.dist-info/top_level.txt
example_pkg_alda_pipeline-0.0.1.dist-info/RECORD
