Metadata-Version: 2.1
Name: example-pkg-alda-pipeline
Version: 0.0.1
Summary: A small example package
Home-page: https://github.com/pypa/alda_pipeline
Author: AlDa
Author-email: author@example.com
License: UNKNOWN
Project-URL: Bug Tracker, https://github.com/pypa/alda_pipeline/issues
Platform: UNKNOWN
Classifier: Programming Language :: Python :: 3
Classifier: License :: OSI Approved :: MIT License
Classifier: Operating System :: OS Independent
Requires-Python: >=3.10
